LICENSE.txt
README.md
setup.py
pacmill/__init__.py
pacmill/run_pacmill.py
pacmill.egg-info/PKG-INFO
pacmill.egg-info/SOURCES.txt
pacmill.egg-info/dependency_links.txt
pacmill.egg-info/requires.txt
pacmill.egg-info/top_level.txt
pacmill/centering/otu_graphs.py
pacmill/centering/otu_table.py
pacmill/centering/vsearch.py
pacmill/core/project.py
pacmill/core/sample.py
pacmill/demo/demo_samples.py
pacmill/demo/download.py
pacmill/demo/sra.py
pacmill/distribute/bundle.py
pacmill/filtering/barrnap.py
pacmill/filtering/chimeras.py
pacmill/filtering/mothur_uchime.py
pacmill/filtering/seq_filter.py
pacmill/reports/base_template.py
pacmill/reports/ncbi_blast/__init__.py
pacmill/reports/project/__init__.py
pacmill/reports/sample/__init__.py
pacmill/reports/taxonomy/__init__.py
pacmill/reports/template/__init__.py
pacmill/statistics/nmds.py
pacmill/taxonomy/crest.py
pacmill/taxonomy/mothur_classify.py
pacmill/taxonomy/multi_database.py
pacmill/taxonomy/ncbi_blast.py
pacmill/taxonomy/taxa_graphs.py
pacmill/taxonomy/taxa_tables.py
scripts/make_small_proj.py
scripts/skip_barrnap.py
scripts/skip_chimeras.py
scripts/tmp_code.py
test/conftest.py
test/barrnap/test_barrnap.py
test/primers/test_primers.py