Metadata-Version: 2.1
Name: pacmill
Version: 0.6.1
Summary: The `pacmill` python package is a bioinformatics pipeline that is developed to process microbial 16S amplicon sequencing data.
Home-page: https://github.com/xapple/pacmill/
Author: Lucas Sinclair
Author-email: lucas.sinclair@me.com
License: MIT
Platform: UNKNOWN
License-File: LICENSE.txt
